polymethod/__init__.py
polymethod/_version.py
polymethod/api.py
polymethod/datastructures.py
polymethod/exceptions.py
polymethod/implementation.py
polymethod/missing.py
polymethod/type_matching.py
polymethod-1.0.0.dist-info/LICENSE
polymethod-1.0.0.dist-info/METADATA
polymethod-1.0.0.dist-info/WHEEL
polymethod-1.0.0.dist-info/top_level.txt
polymethod-1.0.0.dist-info/zip-safe
polymethod-1.0.0.dist-info/RECORD
