Metadata-Version: 2.1
Name: polymethod
Version: 1.0.0
Summary: Library to enable function overloading in Python
Author: Miguel Steiner
Author-email: steiner.mig@gmail.com
License: MIT
Classifier: Programming Language :: Python
Classifier: Development Status :: 5 - Production/Stable
Classifier: Intended Audience :: Developers
Classifier: License :: OSI Approved :: MIT License
Classifier: Natural Language :: English
Requires-Python: >=3.8
License-File: LICENSE
